{"config": {"1STFLRSF": 1146.0, "2NDFLRSF": 785.0, "3SSNPORCH": 140.0, "BEDROOMABVGR": 0.0, "BSMTFINSF1": 867.0, "BSMTFINSF2": 400.0, "BSMTFULLBATH": 1.0, "BSMTHALFBATH": 2.0, "BSMTUNFSF": 999.0, "ENCLOSEDPORCH": 240.0, "FIREPLACES": 2.0, "FULLBATH": 0.0, "GARAGEAREA": 441.0, "GARAGECARS": 2.0, "GARAGEYRBLT": 1966.0, "GRLIVAREA": 1092.0, "HALFBATH": 0.0, "ID": 886.0, "KITCHENABVGR": 2.0, "LOTAREA": 12393.0, "LOTFRONTAGE": 70.0, "LOWQUALFINSF": 420.0, "MASVNRAREA": 328.0, "MISCVAL": 480.0, "MOSOLD": 5.0, "MSSUBCLASS": 180.0, "OPENPORCHSF": 94.0, "POOLAREA": 512.0, "SCREENPORCH": 155.0, "TOTALBSMTSF": 1417.0, "TOTRMSABVGRD": 11.0, "WOODDECKSF": 80.0, "YEARREMODADD": 2003.0, "YRSOLD": 2008.0, "alley": "Grvl", "bldgtype": "1Fam", "bsmtcond": "TA", "bsmtexposure": "Mn", "bsmtfintype1": "Rec", "bsmtfintype2": "Rec", "bsmtqual": "Gd", "centralair": "Y", "condition1": "RRAn", "condition2": "PosN", "electrical": "FuseA", "extercond": "Fa", "exterior1st": "AsbShng", "exterior2nd": "Plywood", "exterqual": "Gd", "fence": "GdPrv", "fireplacequ": "Po", "foundation": "Wood", "functional": "Mod", "garagecond": "Unknown", "garagefinish": "Fin", "garagequal": "TA", "garagetype": "Unknown", "heating": "GasA", "heatingqc": "Gd", "housestyle": "1.5Unf", "kitchenqual": "Ex", "landcontour": "HLS", "landslope": "Mod", "lotconfig": "FR2", "lotshape": "IR2", "masvnrtype": "Stone", "miscfeature": "Shed", "mszoning": "RL", "neighborhood": "Crawfor", "paveddrive": "Y", "poolqc": "Ex", "roofmatl": "WdShake", "roofstyle": "Shed", "salecondition": "Partial", "saletype": "ConLI", "street": "Pave", "utilities": "NoSeWa"}, "score": 0.4260706522865707, "info": {}}