{
  "stats": {
    "submitted": 2,
    "finished": 2,
    "running": 0
  },
  "data": [
    [
      1,
      null,
      418903645,
      null,
      0.16873375549781366,
      1.5962820053100586,
      1,
      1763054079.953727,
      1763054081.856315,
      {}
    ],
    [
      2,
      null,
      418903645,
      null,
      0.23627909096582567,
      1.5413928031921387,
      1,
      1763054081.8691435,
      1763054083.6985128,
      {}
    ]
  ],
  "configs": {
    "1": {
      " ACAP": 4.867,
      " AEXP": 3.602,
      " CPLx": 2.767,
      " DOCU": 4.707,
      " ETAT": 5.055,
      " FLEx": 1.659,
      " KLOC": 204.606,
      " LTEx": 1.452,
      " PCAP": 3.428,
      " PCON": 2.031,
      " PLEx": 2.908,
      " PMAT": 2.489,
      " PREC": 3.089,
      " PVOL": 4.957,
      " RELY": 3.148,
      " RESL": 4.217,
      " RUSE": 4.297,
      " SCED": 3.0,
      " SITE": 4.252,
      " STOR": 3.05,
      " TEAM": 2.442,
      " TIME": 3.371,
      " TOOL": 2.0,
      "DATA": 2.267
    },
    "2": {
      " ACAP": 3.195,
      " AEXP": 4.287,
      " CPLx": 1.738,
      " DOCU": 1.542,
      " ETAT": 2.672,
      " FLEx": 1.326,
      " KLOC": 266.383,
      " LTEx": 3.417,
      " PCAP": 4.966,
      " PCON": 3.538,
      " PLEx": 1.651,
      " PMAT": 2.549,
      " PREC": 3.182,
      " PVOL": 2.704,
      " RELY": 1.339,
      " RESL": 3.006,
      " RUSE": 2.602,
      " SCED": 3.0,
      " SITE": 2.948,
      " STOR": 3.689,
      " TEAM": 2.482,
      " TIME": 3.947,
      " TOOL": 2.0,
      "DATA": 3.83
    }
  },
  "config_origins": {
    "1": "Initial Design: Sobol",
    "2": "Random Search"
  }
}