{
  "incumbent_ids": [
    2
  ],
  "rejected_config_ids": [
    1
  ],
  "incumbents_changed": 2,
  "trajectory": [
    {
      "config_ids": [
        1
      ],
      "costs": [
        0.7982026938113185
      ],
      "trial": 1,
      "walltime": 0.08406710624694824
    },
    {
      "config_ids": [
        2
      ],
      "costs": [
        0.7768445780696757
      ],
      "trial": 2,
      "walltime": 0.17446208000183105
    }
  ],
  "state": {
    "queue": [
      [
        2,
        1
      ]
    ]
  }
}