{
  "incumbent_ids": [
    6
  ],
  "rejected_config_ids": [
    1,
    2,
    4,
    3,
    5,
    7,
    8,
    9,
    10
  ],
  "incumbents_changed": 5,
  "trajectory": [
    {
      "config_ids": [
        1
      ],
      "costs": [
        0.29453267587579535
      ],
      "trial": 1,
      "walltime": 2.0191457271575928
    },
    {
      "config_ids": [
        2
      ],
      "costs": [
        0.2874103209214218
      ],
      "trial": 2,
      "walltime": 3.9064228534698486
    },
    {
      "config_ids": [
        3
      ],
      "costs": [
        0.280419289241581
      ],
      "trial": 3,
      "walltime": 5.436013221740723
    },
    {
      "config_ids": [
        5
      ],
      "costs": [
        0.23719595046215614
      ],
      "trial": 5,
      "walltime": 8.632036924362183
    },
    {
      "config_ids": [
        6
      ],
      "costs": [
        0.18634162939976429
      ],
      "trial": 6,
      "walltime": 10.16211199760437
    }
  ],
  "state": {
    "queue": []
  }
}