{"config": {"Area_km2": 319036.0, "Case_Fatality_Rate": 0.0, "Growth_Factor_of_New_Cases": 3.18, "Growth_Factor_of_New_Deaths": 0.76, "Latitude": -1.69769766, "Longitude": 108.261746, "New_Active_Cases": 974.0, "New_Cases": 104.0, "New_Deaths": 205.0, "New_Deaths_per_Million": 14.2, "New_Recovered": 526.0, "Population": 1307803.0, "Population_Density": 104.88, "Total_Active_Cases": -117.0, "Total_Cases": 6545.0, "Total_Cases_per_Million": 44483.25, "Total_Cities": 8.0, "Total_Deaths": 143519.0, "Total_Districts": 69.0, "Total_Recovered": 25569.0, "Total_Regencies": 6.0, "Total_Rural_Villages": 7724.0, "Total_Urban_Villages": 377.0, "case_Recovered_Rate": 16.63, "city_or_Regency": "?", "continent": "Asia", "country": "Indonesia", "date": "20211010", "island": "Papua", "location": "Indonesia", "location_ISO_Code": "ID-SG", "location_Level": "Country", "province": "Kalimantan Tengah", "special_Status": "Daerah Khusus Ibu Kota", "time_Zone": "UTC+08:00"}, "score": 0.505778634835437, "info": {}}