{"config": {"AGE": 17.0, "FAMILY_RELATIONSHIP": 2.0, "FATHER_EDUCATION": 0.0, "FINAL_GRADE": 5.0, "FREE_TIME": 2.0, "GOING_OUT": 2.0, "GRADE_1": 16.0, "GRADE_2": 9.0, "HEALTH_STATUS": 5.0, "MOTHER_EDUCATION": 0.0, "NUMBER_OF_ABSENCES": 26.0, "NUMBER_OF_FAILURES": 3.0, "STUDY_TIME": 4.0, "TRAVEL_TIME": 4.0, "WEEKDAY_ALCOHOL_CONSUMPTION": 3.0, "WEEKEND_ALCOHOL_CONSUMPTION": 2.0, "address": "U", "attended_nursery": "yes", "extra_curricular_activities": "no", "extra_paid_class": "no", "family_size": "LE3", "family_support": "yes", "father_job": "at_home", "gender": "F", "guardian": "other", "in_relationship": "yes", "internet_access": "no", "mother_job": "health", "parental_status": "A", "reason_for_choosing_school": "course", "school": "MS", "school_support": "yes", "wants_higher_education": "yes"}, "score": 0.0, "info": {}}