{
  "stats": {
    "submitted": 20,
    "finished": 20,
    "running": 0
  },
  "data": [
    [
      1,
      null,
      2005877882,
      null,
      0.0,
      2.621799945831299,
      1,
      1763067464.8544335,
      1763067467.5116847,
      {}
    ],
    [
      2,
      null,
      2005877882,
      null,
      0.0,
      2.342848300933838,
      1,
      1763067467.5178964,
      1763067469.8933885,
      {}
    ],
    [
      3,
      null,
      2005877882,
      null,
      1.0,
      2.6249752044677734,
      1,
      1763067469.8970163,
      1763067472.5566852,
      {}
    ],
    [
      4,
      null,
      2005877882,
      null,
      1.0,
      2.3817248344421387,
      1,
      1763067472.5600116,
      1763067474.9762967,
      {}
    ],
    [
      5,
      null,
      2005877882,
      null,
      0.0,
      2.2766199111938477,
      1,
      1763067474.9796102,
      1763067477.2911692,
      {}
    ],
    [
      6,
      null,
      2005877882,
      null,
      0.0,
      2.2355756759643555,
      1,
      1763067477.294695,
      1763067479.5656033,
      {}
    ],
    [
      7,
      null,
      2005877882,
      null,
      1.0,
      2.7147865295410156,
      1,
      1763067479.5696208,
      1763067482.318426,
      {}
    ],
    [
      8,
      null,
      2005877882,
      null,
      0.0,
      2.2694435119628906,
      1,
      1763067482.3220162,
      1763067484.6358259,
      {}
    ],
    [
      9,
      null,
      2005877882,
      null,
      0.0,
      2.221780776977539,
      1,
      1763067484.6391723,
      1763067486.8940492,
      {}
    ],
    [
      10,
      null,
      2005877882,
      null,
      0.0,
      2.459940195083618,
      1,
      1763067486.8973124,
      1763067489.3913074,
      {}
    ],
    [
      11,
      null,
      2005877882,
      null,
      1.0,
      2.2970190048217773,
      1,
      1763067489.3946474,
      1763067491.7234514,
      {}
    ],
    [
      12,
      null,
      2005877882,
      null,
      0.0,
      2.3481392860412598,
      1,
      1763067491.7272089,
      1763067494.110183,
      {}
    ],
    [
      13,
      null,
      2005877882,
      null,
      0.0,
      2.2639479637145996,
      1,
      1763067494.1145225,
      1763067496.4131277,
      {}
    ],
    [
      14,
      null,
      2005877882,
      null,
      0.0,
      2.2619986534118652,
      1,
      1763067496.4167206,
      1763067498.711725,
      {}
    ],
    [
      15,
      null,
      2005877882,
      null,
      0.0,
      2.056471586227417,
      1,
      1763067498.7155578,
      1763067500.8076444,
      {}
    ],
    [
      16,
      null,
      2005877882,
      null,
      0.0,
      2.0876574516296387,
      1,
      1763067500.8112648,
      1763067502.9334908,
      {}
    ],
    [
      17,
      null,
      2005877882,
      null,
      0.0,
      2.211792230606079,
      1,
      1763067502.937011,
      1763067505.1821115,
      {}
    ],
    [
      18,
      null,
      2005877882,
      null,
      1.0,
      2.338142156600952,
      1,
      1763067505.1861584,
      1763067507.557451,
      {}
    ],
    [
      19,
      null,
      2005877882,
      null,
      0.0,
      2.2379143238067627,
      1,
      1763067507.5623133,
      1763067509.8327894,
      {}
    ],
    [
      20,
      null,
      2005877882,
      null,
      0.0,
      2.2027366161346436,
      1,
      1763067509.8369055,
      1763067512.0719209,
      {}
    ]
  ],
  "configs": {
    "1": {
      "row_id": "1139"
    },
    "2": {
      "row_id": "7467"
    },
    "3": {
      "row_id": "8115"
    },
    "4": {
      "row_id": "4289"
    },
    "5": {
      "row_id": "2570"
    },
    "6": {
      "row_id": "8897"
    },
    "7": {
      "row_id": "5747"
    },
    "8": {
      "row_id": "1921"
    },
    "9": {
      "row_id": "1387"
    },
    "10": {
      "row_id": "5060"
    },
    "11": {
      "row_id": "9430"
    },
    "12": {
      "row_id": "3257"
    },
    "13": {
      "row_id": "4976"
    },
    "14": {
      "row_id": "8649"
    },
    "15": {
      "row_id": "6779"
    },
    "16": {
      "row_id": "605"
    },
    "17": {
      "row_id": "136"
    },
    "18": {
      "row_id": "6306"
    },
    "19": {
      "row_id": "8186"
    },
    "20": {
      "row_id": "4515"
    }
  },
  "config_origins": {
    "1": "Initial Design: Sobol",
    "2": "Initial Design: Sobol",
    "3": "Initial Design: Sobol",
    "4": "Initial Design: Sobol",
    "5": "Initial Design: Sobol",
    "6": "Initial Design: Sobol",
    "7": "Initial Design: Sobol",
    "8": "Initial Design: Sobol",
    "9": "Initial Design: Sobol",
    "10": "Initial Design: Sobol",
    "11": "Initial Design: Sobol",
    "12": "Initial Design: Sobol",
    "13": "Initial Design: Sobol",
    "14": "Initial Design: Sobol",
    "15": "Initial Design: Sobol",
    "16": "Initial Design: Sobol",
    "17": "Initial Design: Sobol",
    "18": "Initial Design: Sobol",
    "19": "Initial Design: Sobol",
    "20": "Initial Design: Sobol"
  }
}