{
  "stats": {
    "submitted": 5,
    "finished": 5,
    "running": 0
  },
  "data": [
    [
      1,
      null,
      1192722770,
      null,
      0.6288085084196537,
      2.717020034790039,
      1,
      1763062658.855268,
      1763062661.6244977,
      {}
    ],
    [
      2,
      null,
      1192722770,
      null,
      0.570824572807963,
      2.5136654376983643,
      1,
      1763062661.6298485,
      1763062664.179829,
      {}
    ],
    [
      3,
      null,
      1192722770,
      null,
      0.6474910014876165,
      2.1350791454315186,
      1,
      1763062664.1829574,
      1763062666.3545094,
      {}
    ],
    [
      4,
      null,
      1192722770,
      null,
      0.6231944280641741,
      2.3300435543060303,
      1,
      1763062666.3572114,
      1763062668.7204163,
      {}
    ],
    [
      5,
      null,
      1192722770,
      null,
      0.6492681716099563,
      2.641961097717285,
      1,
      1763062668.7232985,
      1763062671.3967147,
      {}
    ]
  ],
  "configs": {
    "1": {
      "row_id": "5629"
    },
    "2": {
      "row_id": "832"
    },
    "3": {
      "row_id": "4056"
    },
    "4": {
      "row_id": "8851"
    },
    "5": {
      "row_id": "8402"
    }
  },
  "config_origins": {
    "1": "Initial Design: Sobol",
    "2": "Initial Design: Sobol",
    "3": "Initial Design: Sobol",
    "4": "Initial Design: Sobol",
    "5": "Initial Design: Sobol"
  }
}