{
  "stats": {
    "submitted": 1,
    "finished": 1,
    "running": 0
  },
  "data": [
    [
      1,
      null,
      959027881,
      null,
      0.2792155630646277,
      2.932112455368042,
      1,
      1763054164.5575035,
      1763054167.7736459,
      {}
    ]
  ],
  "configs": {
    "1": {
      " ACAP": 3.987,
      " AEXP": 4.069,
      " CPLx": 3.829,
      " DOCU": 2.54,
      " ETAT": 1.633,
      " FLEx": 4.534,
      " KLOC": 283.378,
      " LTEx": 3.213,
      " PCAP": 4.317,
      " PCON": 2.721,
      " PLEx": 3.051,
      " PMAT": 2.537,
      " PREC": 4.467,
      " PVOL": 3.54,
      " RELY": 2.148,
      " RESL": 1.575,
      " RUSE": 5.038,
      " SCED": 3.0,
      " SITE": 2.089,
      " STOR": 3.467,
      " TEAM": 2.99,
      " TIME": 3.709,
      " TOOL": 2.0,
      "DATA": 2.523
    }
  },
  "config_origins": {
    "1": "Initial Design: Sobol"
  }
}