{
  "DE_params": {
    "mutation_factor": 0.5,
    "crossover_prob": 0.5,
    "strategy": "rand1_bin",
    "configspace": true,
    "boundary_fix_type": "random",
    "max_age": Infinity,
    "dimensions": 19,
    "output_path": "../results/tmp/DEHB_tmp/dehb_20251208-045010_f1cf",
    "async_strategy": "immediate"
  },
  "HB_params": {
    "min_fidelity": 1,
    "max_fidelity": 10,
    "min_clip": null,
    "max_clip": null,
    "eta": 3
  },
  "internals": {
    "initial_configs": [
      {
        "config_id": 0,
        "config": [
          0.22510373443983403,
          0.3029525032092426,
          0.7142857142857143,
          0.6666666666666666,
          0.5,
          0.8571428571428571,
          0.25,
          0.29666876178504087,
          0.053125,
          0.7590673575129534,
          0.5,
          0.15239419829127757,
          0.6111111111111112,
          0.5,
          0.5,
          0.2857142857142857,
          0.5,
          0.5,
          0.25
        ],
        "results": {
          "1.1111111111111112": {
            "score": Infinity,
            "cost": -1,
            "info": {}
          }
        }
      },
      {
        "config_id": 1,
        "config": [
          0.9097510373443983,
          0.004147328922681939,
          0.0,
          0.2222222222222222,
          0.0,
          0.42857142857142855,
          0.8863636363636364,
          0.33752357008170963,
          0.765625,
          0.27461139896373055,
          0.3333333333333333,
          0.3488972779654282,
          0.8015873015873016,
          0.5,
          0.25,
          0.0,
          0.5,
          0.6666666666666666,
          0.0
        ],
        "results": {
          "1.1111111111111112": {
            "score": Infinity,
            "cost": -1,
            "info": {}
          }
        }
      },
      {
        "config_id": 2,
        "config": [
          0.491701244813278,
          0.1885059741285672,
          0.7142857142857143,
          0.6,
          0.5,
          0.5714285714285714,
          0.13636363636363635,
          0.7473287240729101,
          0.3890625,
          0.8773747841105354,
          0.8333333333333334,
          0.17266044108881382,
          0.8809523809523809,
          0.0,
          0.0,
          0.8571428571428571,
          0.0,
          0.5,
          0.5
        ],
        "results": {
          "1.1111111111111112": {
            "score": Infinity,
            "cost": -1,
            "info": {}
          }
        }
      },
      {
        "config_id": 3,
        "config": [
          0.18672199170124482,
          0.7036634738817024,
          0.42857142857142855,
          0.044444444444444446,
          0.3333333333333333,
          0.8571428571428571,
          0.29545454545454547,
          0.8265241986172219,
          0.4953125,
          0.3765112262521589,
          0.0,
          0.02940592092191536,
          0.30158730158730157,
          0.5,
          0.0,
          0.42857142857142855,
          0.5,
          0.0,
          0.5
        ],
        "results": {
          "1.1111111111111112": {
            "score": Infinity,
            "cost": -1,
            "info": {}
          }
        }
      },
      {
        "config_id": 4,
        "config": [
          0.6120331950207469,
          0.7810802804384319,
          0.5714285714285714,
          0.044444444444444446,
          0.3333333333333333,
          0.2857142857142857,
          0.5227272727272727,
          0.6209930861093652,
          0.0671875,
          0.6122625215889465,
          0.16666666666666666,
          0.731969004569839,
          0.49206349206349204,
          0.0,
          0.25,
          0.42857142857142855,
          0.0,
          0.16666666666666666,
          0.5
        ],
        "results": {
          "1.1111111111111112": {
            "score": Infinity,
            "cost": -1,
            "info": {}
          }
        }
      },
      {
        "config_id": 5,
        "config": [
          0.8734439834024896,
          0.4138441789276192,
          0.8571428571428571,
          0.8888888888888888,
          0.6666666666666666,
          0.0,
          0.5227272727272727,
          0.4424890006285355,
          0.8078125,
          0.08635578583765112,
          0.6666666666666666,
          0.5781839856944169,
          0.047619047619047616,
          0.0,
          0.0,
          0.14285714285714285,
          0.0,
          0.16666666666666666,
          0.0
        ],
        "results": {
          "1.1111111111111112": {
            "score": Infinity,
            "cost": -1,
            "info": {}
          }
        }
      },
      {
        "config_id": 6,
        "config": [
          0.5964730290456431,
          0.37582699713636813,
          0.14285714285714285,
          0.2222222222222222,
          0.3333333333333333,
          0.42857142857142855,
          0.3409090909090909,
          0.7768698931489629,
          0.6375,
          0.5371329879101899,
          0.16666666666666666,
          0.9554937413073713,
          0.8333333333333334,
          0.0,
          0.25,
          0.2857142857142857,
          0.5,
          0.16666666666666666,
          0.25
        ],
        "results": {
          "1.1111111111111112": {
            "score": Infinity,
            "cost": -1,
            "info": {}
          }
        }
      },
      {
        "config_id": 7,
        "config": [
          0.7396265560165975,
          0.23254665745038017,
          0.0,
          0.5777777777777777,
          0.16666666666666666,
          0.0,
          0.29545454545454547,
          0.5883092394720302,
          0.2375,
          0.9766839378238342,
          0.8333333333333334,
          0.25591098748261476,
          0.42063492063492064,
          0.0,
          0.25,
          0.2857142857142857,
          0.5,
          0.6666666666666666,
          0.75
        ],
        "results": {
          "1.1111111111111112": {
            "score": Infinity,
            "cost": -1,
            "info": {}
          }
        }
      },
      {
        "config_id": 8,
        "config": [
          0.8890041493775933,
          0.534215463612126,
          0.5714285714285714,
          0.35555555555555557,
          0.8333333333333334,
          0.8571428571428571,
          0.29545454545454547,
          0.3004399748585795,
          0.3765625,
          0.047495682210708115,
          0.3333333333333333,
          0.38545599046294454,
          0.753968253968254,
          0.0,
          0.75,
          0.7142857142857143,
          0.5,
          0.8333333333333334,
          0.25
        ],
        "results": {
          "1.1111111111111112": {
            "score": Infinity,
            "cost": -1,
            "info": {}
          }
        }
      },
      {
        "config_id": 9,
        "config": [
          0.9398340248962656,
          0.30226128172212896,
          0.7142857142857143,
          0.15555555555555556,
          0.0,
          0.8571428571428571,
          0.25,
          0.5694531741043369,
          0.7046875,
          0.2711571675302245,
          0.6666666666666666,
          0.0949731770315915,
          0.20634920634920634,
          0.5,
          0.25,
          0.7142857142857143,
          0.0,
          0.16666666666666666,
          0.5
        ],
        "results": {
          "3.333333333333333": {
            "score": Infinity,
            "cost": -1,
            "info": {}
          }
        }
      },
      {
        "config_id": 10,
        "config": [
          0.04149377593360996,
          0.7530364372469636,
          0.8571428571428571,
          0.4444444444444444,
          0.5,
          0.7142857142857143,
          0.7045454545454546,
          0.9773727215587681,
          0.1890625,
          0.6882556131260794,
          0.0,
          0.36141466322272997,
          0.6111111111111112,
          0.0,
          0.75,
          0.5714285714285714,
          0.5,
          0.3333333333333333,
          0.75
        ],
        "results": {
          "3.333333333333333": {
            "score": Infinity,
            "cost": -1,
            "info": {}
          }
        }
      },
      {
        "config_id": 11,
        "config": [
          0.1607883817427386,
          0.5443862940653698,
          0.2857142857142857,
          0.4,
          0.0,
          0.5714285714285714,
          0.8863636363636364,
          0.623507228158391,
          0.759375,
          0.04231433506044905,
          0.16666666666666666,
          0.2418040929862905,
          0.7063492063492064,
          0.5,
          0.0,
          0.0,
          0.0,
          0.8333333333333334,
          0.75
        ],
        "results": {
          "3.333333333333333": {
            "score": Infinity,
            "cost": -1,
            "info": {}
          }
        }
      },
      {
        "config_id": 12,
        "config": [
          0.5923236514522822,
          0.11434778315394489,
          0.14285714285714285,
          0.4444444444444444,
          0.3333333333333333,
          0.2857142857142857,
          0.4090909090909091,
          0.2143306096794469,
          0.1,
          0.3290155440414508,
          0.6666666666666666,
          0.7198489966222928,
          0.7857142857142857,
          0.5,
          0.75,
          0.0,
          0.0,
          0.8333333333333334,
          0.25
        ],
        "results": {
          "10.0": {
            "score": Infinity,
            "cost": -1,
            "info": {}
          }
        }
      },
      {
        "config_id": 13,
        "config": [
          0.26867219917012447,
          0.8900957835489286,
          0.0,
          0.7777777777777778,
          0.6666666666666666,
          0.14285714285714285,
          0.022727272727272728,
          0.16404776869893148,
          0.171875,
          0.9879101899827288,
          0.6666666666666666,
          0.7554142658454203,
          0.23809523809523808,
          0.5,
          0.75,
          0.7142857142857143,
          0.0,
          0.8333333333333334,
          0.5
        ],
        "results": {
          "10.0": {
            "score": Infinity,
            "cost": -1,
            "info": {}
          }
        }
      },
      {
        "config_id": 14,
        "config": [
          0.39107883817427386,
          0.021526612027253877,
          0.0,
          0.4666666666666667,
          0.3333333333333333,
          0.7142857142857143,
          0.3181818181818182,
          0.08673790069138906,
          0.0546875,
          0.3316062176165803,
          0.16666666666666666,
          0.6063977746870653,
          0.2777777777777778,
          0.5,
          0.75,
          0.5714285714285714,
          0.5,
          0.6666666666666666,
          0.0
        ],
        "results": {
          "10.0": {
            "score": Infinity,
            "cost": -1,
            "info": {}
          }
        }
      }
    ]
  }
}