{
  "stats": {
    "submitted": 2,
    "finished": 2,
    "running": 0
  },
  "data": [
    [
      1,
      null,
      378518883,
      null,
      0.6699569062121853,
      2.0548019409179688,
      1,
      1763061943.6189096,
      1763061945.705872,
      {}
    ],
    [
      2,
      null,
      378518883,
      null,
      0.7960409131263517,
      1.9937715530395508,
      1,
      1763061945.7086325,
      1763061947.746964,
      {}
    ]
  ],
  "configs": {
    "1": {
      "row_id": "853"
    },
    "2": {
      "row_id": "9130"
    }
  },
  "config_origins": {
    "1": "Initial Design: Sobol",
    "2": "Initial Design: Sobol"
  }
}