{"config": {"SeniorCitizen": 0.0, "churn": "Yes", "contract": "One_year", "customerID": "6198_RTPMF", "dependents": "No", "deviceProtection": "No_internet_service", "gender": "Male", "internetService": "Fiber_optic", "multipleLines": "No_phone_service", "onlineBackup": "No_internet_service", "onlineSecurity": "No_internet_service", "paperlessBilling": "No", "partner": "Yes", "paymentMethod": "Mailed_check", "phoneService": "No", "streamingMovies": "No_internet_service", "streamingTV": "No_internet_service", "techSupport": "No", "tenure": 3.0}, "score": 0.0074282384216445285, "info": {}}