{"config": {"Area_km2": 61841.0, "Case_Fatality_Rate": 0.0, "Growth_Factor_of_New_Cases": 5.14, "Growth_Factor_of_New_Deaths": 0.35, "Latitude": -6.456736388, "Longitude": 116.4684405, "New_Active_Cases": -467.0, "New_Cases": 61.0, "New_Deaths": 1568.0, "New_Deaths_per_Million": 6.79, "New_Recovered": 950.0, "Population": 40479023.0, "Population_Density": 111.07, "Total_Active_Cases": 58072.0, "Total_Cases": 398881.0, "Total_Cases_per_Million": 2463.01, "Total_Cities": 2.0, "Total_Deaths": 758.0, "Total_Districts": 47.0, "Total_Recovered": 144954.0, "Total_Regencies": 4.0, "Total_Rural_Villages": 5411.0, "Total_Urban_Villages": 175.0, "case_Recovered_Rate": 17.07, "city_or_Regency": "?", "continent": "Asia", "country": "Indonesia", "date": "20201128", "island": "Papua", "location": "Kalimantan Selatan", "location_ISO_Code": "ID-RI", "location_Level": "Province", "province": "Kepulauan Riau", "special_Status": "Daerah Khusus", "time_Zone": "UTC+09:00"}, "score": 0.7357657937802551, "info": {}}