{"config": {" BMI ": 5.2, " HIV/AIDS": 10.7, " thinness  1-19 years": 5.4, " thinness 5-9 years": 0.3, "Adult Mortality": 298.0, "Alcohol": 12.21, "Diphtheria ": 16.0, "GDP": 9692.163874, "Hepatitis B": 24.0, "Life expectancy ": 71.4, "Measles ": 65.0, "Polio": 38.0, "Population": 1478617.0, "Total expenditure": 5.12, "Year": 2012.0, "country": "Panama", "infant deaths": 44.0, "percentage expenditure": 1154.893473, "status": "Developing", "under-five deaths ": 18.0}, "score": 0.24083179300185442, "info": {}}