{
  "stats": {
    "submitted": 9,
    "finished": 9,
    "running": 0
  },
  "data": [
    [
      1,
      null,
      327741615,
      null,
      0.0,
      2.175808906555176,
      1,
      1763066931.8383448,
      1763066934.047863,
      {}
    ],
    [
      2,
      null,
      327741615,
      null,
      0.0,
      2.1571667194366455,
      1,
      1763066934.0580347,
      1763066936.250054,
      {}
    ],
    [
      3,
      null,
      327741615,
      null,
      1.0,
      2.242464065551758,
      1,
      1763067020.3285918,
      1763067022.6099339,
      {}
    ],
    [
      4,
      null,
      327741615,
      null,
      0.0,
      2.1126394271850586,
      1,
      1763067022.6130977,
      1763067024.758761,
      {}
    ],
    [
      5,
      null,
      327741615,
      null,
      0.0,
      2.185257911682129,
      1,
      1763067024.7622185,
      1763067026.9815273,
      {}
    ],
    [
      6,
      null,
      327741615,
      null,
      0.0,
      2.0980358123779297,
      1,
      1763067026.9849794,
      1763067029.116201,
      {}
    ],
    [
      7,
      null,
      327741615,
      null,
      0.0,
      2.117372751235962,
      1,
      1763067029.1197262,
      1763067031.2704062,
      {}
    ],
    [
      8,
      null,
      327741615,
      null,
      0.0,
      2.076313018798828,
      1,
      1763067031.274023,
      1763067033.3850036,
      {}
    ],
    [
      9,
      null,
      327741615,
      null,
      1.0,
      1.9937779903411865,
      1,
      1763067033.3893704,
      1763067035.4171448,
      {}
    ]
  ],
  "configs": {
    "1": {
      "row_id": "7333"
    },
    "2": {
      "row_id": "763"
    },
    "3": {
      "row_id": "1240"
    },
    "4": {
      "row_id": "9135"
    },
    "5": {
      "row_id": "3717"
    },
    "6": {
      "row_id": "6840"
    },
    "7": {
      "row_id": "8254"
    },
    "8": {
      "row_id": "2563"
    },
    "9": {
      "row_id": "9724"
    }
  },
  "config_origins": {
    "1": "Initial Design: Sobol",
    "2": "Random Search",
    "3": "Acquisition Function Maximizer: Local Search",
    "4": "Acquisition Function Maximizer: Local Search",
    "5": "Acquisition Function Maximizer: Local Search",
    "6": "Acquisition Function Maximizer: Local Search",
    "7": "Acquisition Function Maximizer: Local Search",
    "8": "Acquisition Function Maximizer: Local Search",
    "9": "Random Search"
  }
}