{
  "incumbent_ids": [
    37
  ],
  "rejected_config_ids": [
    2,
    1,
    4,
    5,
    6,
    3,
    8,
    9,
    10,
    11,
    12,
    13,
    14,
    15,
    16,
    17,
    18,
    19,
    20,
    21,
    22,
    23,
    24,
    25,
    26,
    27,
    28,
    29,
    30,
    31,
    32,
    33,
    34,
    35,
    7,
    36,
    38,
    39,
    40,
    41,
    42,
    43,
    44,
    45,
    46,
    47,
    48,
    49,
    50
  ],
  "incumbents_changed": 5,
  "trajectory": [
    {
      "config_ids": [
        1
      ],
      "costs": [
        0.7899004182853481
      ],
      "trial": 1,
      "walltime": 0.009743690490722656
    },
    {
      "config_ids": [
        3
      ],
      "costs": [
        0.7829218389747442
      ],
      "trial": 3,
      "walltime": 0.020880699157714844
    },
    {
      "config_ids": [
        7
      ],
      "costs": [
        0.7315724664374735
      ],
      "trial": 7,
      "walltime": 0.0500941276550293
    },
    {
      "config_ids": [
        36
      ],
      "costs": [
        0.41400315432576107
      ],
      "trial": 36,
      "walltime": 6.454028367996216
    },
    {
      "config_ids": [
        37
      ],
      "costs": [
        0.382934598913768
      ],
      "trial": 37,
      "walltime": 6.465256214141846
    }
  ],
  "state": {
    "queue": [
      [
        50,
        1
      ]
    ]
  }
}