{
  "stats": {
    "submitted": 9,
    "finished": 9,
    "running": 0
  },
  "data": [
    [
      1,
      null,
      418903645,
      null,
      0.5352652386804555,
      0.2503535747528076,
      1,
      1763062862.4431114,
      1763062862.7004218,
      {}
    ],
    [
      2,
      null,
      418903645,
      null,
      0.48186030041125605,
      0.2853381633758545,
      1,
      1763062862.704927,
      1763062862.9967947,
      {}
    ],
    [
      3,
      null,
      418903645,
      null,
      0.356843492453637,
      0.2741396427154541,
      1,
      1763062878.045849,
      1763062878.3267374,
      {}
    ],
    [
      4,
      null,
      418903645,
      null,
      0.5099019513592784,
      0.27161693572998047,
      1,
      1763062878.330667,
      1763062878.6088076,
      {}
    ],
    [
      5,
      null,
      418903645,
      null,
      0.3440104580768908,
      0.33763861656188965,
      1,
      1763062878.6124928,
      1763062878.9569135,
      {}
    ],
    [
      6,
      null,
      418903645,
      null,
      0.33793665594598155,
      0.30220508575439453,
      1,
      1763062878.9617085,
      1763062879.27134,
      {}
    ],
    [
      7,
      null,
      418903645,
      null,
      0.42662844996498595,
      0.30808448791503906,
      1,
      1763062879.2763317,
      1763062879.5913339,
      {}
    ],
    [
      8,
      null,
      418903645,
      null,
      0.4575468417834785,
      0.3150181770324707,
      1,
      1763062879.5960927,
      1763062879.9190512,
      {}
    ],
    [
      9,
      null,
      418903645,
      null,
      0.48186030041125605,
      0.3359355926513672,
      1,
      1763062879.9234176,
      1763062880.266316,
      {}
    ]
  ],
  "configs": {
    "1": {
      "row_id": "1491"
    },
    "2": {
      "row_id": "155"
    },
    "3": {
      "row_id": "1025"
    },
    "4": {
      "row_id": "1078"
    },
    "5": {
      "row_id": "436"
    },
    "6": {
      "row_id": "269"
    },
    "7": {
      "row_id": "944"
    },
    "8": {
      "row_id": "947"
    },
    "9": {
      "row_id": "707"
    }
  },
  "config_origins": {
    "1": "Initial Design: Sobol",
    "2": "Random Search",
    "3": "Acquisition Function Maximizer: Local Search",
    "4": "Acquisition Function Maximizer: Local Search",
    "5": "Random Search",
    "6": "Acquisition Function Maximizer: Local Search",
    "7": "Random Search",
    "8": "Acquisition Function Maximizer: Local Search",
    "9": "Acquisition Function Maximizer: Local Search"
  }
}