{
  "stats": {
    "submitted": 5,
    "finished": 5,
    "running": 0
  },
  "data": [
    [
      1,
      null,
      774252441,
      null,
      0.5661698426841941,
      2.693284749984741,
      1,
      1763062658.7899163,
      1763062661.5237806,
      {}
    ],
    [
      2,
      null,
      774252441,
      null,
      0.5812946664058857,
      2.551708936691284,
      1,
      1763062661.5291831,
      1763062664.1151524,
      {}
    ],
    [
      3,
      null,
      774252441,
      null,
      0.6372456191533532,
      2.10382080078125,
      1,
      1763062664.1180234,
      1763062666.2544744,
      {}
    ],
    [
      4,
      null,
      774252441,
      null,
      0.45520664295774327,
      2.447023391723633,
      1,
      1763062666.258057,
      1763062668.739163,
      {}
    ],
    [
      5,
      null,
      774252441,
      null,
      0.6154916171102671,
      2.4153642654418945,
      1,
      1763062668.7438388,
      1763062671.1943305,
      {}
    ]
  ],
  "configs": {
    "1": {
      "row_id": "6184"
    },
    "2": {
      "row_id": "1052"
    },
    "3": {
      "row_id": "2931"
    },
    "4": {
      "row_id": "8112"
    },
    "5": {
      "row_id": "9782"
    }
  },
  "config_origins": {
    "1": "Initial Design: Sobol",
    "2": "Initial Design: Sobol",
    "3": "Initial Design: Sobol",
    "4": "Initial Design: Sobol",
    "5": "Initial Design: Sobol"
  }
}