{
  "incumbent_ids": [
    86
  ],
  "rejected_config_ids": [
    2,
    3,
    1,
    5,
    6,
    7,
    8,
    9,
    10,
    11,
    12,
    13,
    14,
    15,
    16,
    17,
    18,
    19,
    4,
    21,
    22,
    23,
    24,
    25,
    26,
    27,
    28,
    29,
    30,
    31,
    32,
    33,
    34,
    35,
    36,
    37,
    38,
    39,
    40,
    41,
    42,
    43,
    44,
    45,
    46,
    47,
    48,
    49,
    50,
    51,
    52,
    53,
    54,
    55,
    56,
    57,
    58,
    59,
    60,
    61,
    62,
    63,
    64,
    65,
    66,
    67,
    68,
    69,
    70,
    71,
    72,
    73,
    74,
    75,
    76,
    77,
    78,
    79,
    80,
    81,
    82,
    83,
    84,
    85,
    20,
    87,
    88,
    89,
    90,
    91,
    92,
    93,
    94,
    95,
    96,
    97,
    98,
    99,
    100
  ],
  "incumbents_changed": 4,
  "trajectory": [
    {
      "config_ids": [
        1
      ],
      "costs": [
        0.36477577677132866
      ],
      "trial": 1,
      "walltime": 0.016999244689941406
    },
    {
      "config_ids": [
        4
      ],
      "costs": [
        0.2992013752766034
      ],
      "trial": 4,
      "walltime": 0.06465506553649902
    },
    {
      "config_ids": [
        20
      ],
      "costs": [
        0.2466481266908025
      ],
      "trial": 20,
      "walltime": 3.112795829772949
    },
    {
      "config_ids": [
        86
      ],
      "costs": [
        0.23267232949125216
      ],
      "trial": 86,
      "walltime": 34.694865226745605
    }
  ],
  "state": {
    "queue": [
      [
        100,
        1
      ]
    ]
  }
}