{"config": {"Area_km2": 72981.0, "Case_Fatality_Rate": 0.0, "Growth_Factor_of_New_Cases": 5.54, "Growth_Factor_of_New_Deaths": 1.62, "Latitude": -4.916792975, "Longitude": 117.5086257, "New_Active_Cases": -35.0, "New_Cases": 1079.0, "New_Deaths": 427.0, "New_Deaths_per_Million": 0.72, "New_Recovered": 4113.0, "Population": 5270247.0, "Population_Density": 16334.31, "Total_Active_Cases": 572.0, "Total_Cases": 94328.0, "Total_Cases_per_Million": 40118.59, "Total_Cities": 9.0, "Total_Deaths": 10223.0, "Total_Districts": 171.0, "Total_Recovered": 107124.0, "Total_Regencies": 10.0, "Total_Rural_Villages": 1063.0, "Total_Urban_Villages": 142.0, "case_Recovered_Rate": 20.08, "city_or_Regency": "?", "continent": "Asia", "country": "Indonesia", "date": "20210614", "island": "Papua", "location": "Kalimantan Barat", "location_ISO_Code": "ID-BE", "location_Level": "Province", "province": "Sulawesi Selatan", "special_Status": "?", "time_Zone": "UTC+07:00"}, "score": 0.6310932280803803, "info": {}}