{
  "stats": {
    "submitted": 10,
    "finished": 10,
    "running": 0
  },
  "data": [
    [
      1,
      null,
      44556670,
      null,
      0.15993326559554122,
      1.7469170093536377,
      1,
      1763060882.7435317,
      1763060884.5266275,
      {}
    ],
    [
      2,
      null,
      44556670,
      null,
      0.26356942558203134,
      2.114175796508789,
      1,
      1763060884.5347505,
      1763060886.6843202,
      {}
    ],
    [
      3,
      null,
      44556670,
      null,
      0.08647489260191843,
      1.6975038051605225,
      1,
      1763060886.687393,
      1763060888.4229667,
      {}
    ],
    [
      4,
      null,
      44556670,
      null,
      0.27003873433841064,
      1.6810259819030762,
      1,
      1763060888.4262445,
      1763060890.1407192,
      {}
    ],
    [
      5,
      null,
      44556670,
      null,
      0.3673067845959239,
      1.5510258674621582,
      1,
      1763060890.1436136,
      1763060891.738034,
      {}
    ],
    [
      6,
      null,
      44556670,
      null,
      0.1801421936428007,
      1.6281027793884277,
      1,
      1763060891.7410178,
      1763060893.4035745,
      {}
    ],
    [
      7,
      null,
      44556670,
      null,
      0.3054216418639435,
      1.7275588512420654,
      1,
      1763060893.4069014,
      1763060895.1686647,
      {}
    ],
    [
      8,
      null,
      44556670,
      null,
      0.14340984508531074,
      1.714493989944458,
      1,
      1763060895.1717741,
      1763060896.9198349,
      {}
    ],
    [
      9,
      null,
      44556670,
      null,
      0.21398385539879938,
      1.6531758308410645,
      1,
      1763060896.9231682,
      1763060898.6104167,
      {}
    ],
    [
      10,
      null,
      44556670,
      null,
      0.3575803860407356,
      1.7298507690429688,
      1,
      1763060898.6147206,
      1763060900.3775928,
      {}
    ]
  ],
  "configs": {
    "1": {
      "row_id": "211"
    },
    "2": {
      "row_id": "5507"
    },
    "3": {
      "row_id": "8969"
    },
    "4": {
      "row_id": "4226"
    },
    "5": {
      "row_id": "3434"
    },
    "6": {
      "row_id": "8690"
    },
    "7": {
      "row_id": "7154"
    },
    "8": {
      "row_id": "2449"
    },
    "9": {
      "row_id": "1809"
    },
    "10": {
      "row_id": "6552"
    }
  },
  "config_origins": {
    "1": "Initial Design: Sobol",
    "2": "Initial Design: Sobol",
    "3": "Initial Design: Sobol",
    "4": "Initial Design: Sobol",
    "5": "Initial Design: Sobol",
    "6": "Initial Design: Sobol",
    "7": "Initial Design: Sobol",
    "8": "Initial Design: Sobol",
    "9": "Initial Design: Sobol",
    "10": "Initial Design: Sobol"
  }
}