{
  "DE_params": {
    "mutation_factor": 0.5,
    "crossover_prob": 0.5,
    "strategy": "rand1_bin",
    "configspace": true,
    "boundary_fix_type": "random",
    "max_age": Infinity,
    "dimensions": 32,
    "output_path": "../results/tmp/DEHB_tmp/dehb_20251208-050208_bf0c",
    "async_strategy": "immediate"
  },
  "HB_params": {
    "min_fidelity": 1,
    "max_fidelity": 10,
    "min_clip": null,
    "max_clip": null,
    "eta": 3
  },
  "internals": {
    "initial_configs": [
      {
        "config_id": 0,
        "config": [
          0.6744186046511628,
          0.06772009029345373,
          0.3793103448275862,
          0.6,
          0.0,
          0.7986394557823129,
          0.0,
          0.07042253521126761,
          0.5,
          0.4,
          0.75,
          0.4128984432913269,
          0.3559915907498248,
          0.4,
          0.5333333333333333,
          0.5,
          0.75,
          0.0,
          0.0,
          0.125,
          0.8571428571428571,
          0.0,
          0.3125,
          0.5,
          0.6666666666666666,
          0.6666666666666666,
          0.5,
          0.0,
          0.4444444444444444,
          0.0,
          0.0,
          0.0
        ],
        "results": {
          "1.1111111111111112": {
            "score": Infinity,
            "cost": -1,
            "info": {}
          }
        }
      },
      {
        "config_id": 1,
        "config": [
          0.7441860465116279,
          0.6715575620767494,
          0.1724137931034483,
          0.2,
          0.0,
          0.8707482993197279,
          0.75,
          0.23943661971830985,
          0.75,
          0.6,
          0.25,
          0.7412898443291327,
          0.7561317449194114,
          0.0,
          0.06666666666666667,
          0.5,
          0.5,
          0.0,
          0.75,
          0.85,
          0.42857142857142855,
          0.25,
          0.375,
          0.5,
          0.0,
          0.6666666666666666,
          0.6666666666666666,
          0.5,
          0.8888888888888888,
          0.3333333333333333,
          0.0,
          0.0
        ],
        "results": {
          "1.1111111111111112": {
            "score": Infinity,
            "cost": -1,
            "info": {}
          }
        }
      },
      {
        "config_id": 2,
        "config": [
          0.06976744186046512,
          0.01580135440180587,
          0.5517241379310345,
          0.0,
          0.0,
          0.27346938775510204,
          0.5,
          0.04225352112676056,
          0.25,
          0.8,
          0.0,
          0.04002965159377316,
          0.7792571829011913,
          0.6,
          0.3333333333333333,
          0.5,
          0.0,
          0.0,
          0.75,
          0.5,
          0.14285714285714285,
          0.25,
          0.125,
          0.0,
          0.6666666666666666,
          0.3333333333333333,
          0.0,
          0.5,
          0.0,
          0.3333333333333333,
          0.0,
          0.5
        ],
        "results": {
          "1.1111111111111112": {
            "score": Infinity,
            "cost": -1,
            "info": {}
          }
        }
      },
      {
        "config_id": 3,
        "config": [
          0.32558139534883723,
          0.6873589164785553,
          0.6206896551724138,
          0.6,
          0.0,
          0.9564625850340136,
          0.5,
          0.9014084507042254,
          0.25,
          0.4,
          0.25,
          0.2535211267605634,
          0.41345480028030834,
          0.0,
          0.13333333333333333,
          0.5,
          0.25,
          0.0,
          0.25,
          0.925,
          0.42857142857142855,
          0.25,
          0.6875,
          0.0,
          0.6666666666666666,
          0.6666666666666666,
          0.0,
          0.0,
          0.0,
          0.6666666666666666,
          0.0,
          0.5
        ],
        "results": {
          "1.1111111111111112": {
            "score": Infinity,
            "cost": -1,
            "info": {}
          }
        }
      },
      {
        "config_id": 4,
        "config": [
          0.4418604651162791,
          0.48419864559819414,
          0.5517241379310345,
          0.6,
          0.0,
          0.2272108843537415,
          0.75,
          0.2112676056338028,
          0.75,
          0.0,
          0.25,
          0.5300222386953298,
          0.035739313244569026,
          0.8,
          0.26666666666666666,
          0.5,
          0.5,
          0.0,
          0.25,
          0.2,
          0.8571428571428571,
          0.5,
          0.375,
          0.0,
          0.3333333333333333,
          0.3333333333333333,
          0.8333333333333334,
          0.5,
          0.1111111111111111,
          0.0,
          0.0,
          0.5
        ],
        "results": {
          "1.1111111111111112": {
            "score": Infinity,
            "cost": -1,
            "info": {}
          }
        }
      },
      {
        "config_id": 5,
        "config": [
          0.4418604651162791,
          0.24040632054176073,
          0.13793103448275862,
          0.4,
          0.0,
          0.21836734693877552,
          0.25,
          0.5915492957746479,
          0.5,
          0.2,
          0.25,
          0.8650852483320979,
          0.08689558514365803,
          0.8,
          0.4,
          0.5,
          0.75,
          0.0,
          0.5,
          0.75,
          0.42857142857142855,
          0.25,
          0.25,
          0.0,
          0.6666666666666666,
          0.3333333333333333,
          0.3333333333333333,
          0.5,
          0.4444444444444444,
          0.3333333333333333,
          0.0,
          0.5
        ],
        "results": {
          "1.1111111111111112": {
            "score": Infinity,
            "cost": -1,
            "info": {}
          }
        }
      },
      {
        "config_id": 6,
        "config": [
          0.6744186046511628,
          0.6930022573363431,
          0.1724137931034483,
          0.8,
          0.0,
          0.7523809523809524,
          0.5,
          0.9154929577464789,
          0.5,
          0.6,
          0.25,
          0.4588584136397331,
          0.7182901191310441,
          0.7,
          0.4666666666666667,
          0.5,
          0.25,
          0.0,
          0.5,
          0.775,
          0.7142857142857143,
          0.0,
          0.4375,
          0.0,
          0.3333333333333333,
          0.0,
          0.0,
          0.0,
          0.5555555555555556,
          0.6666666666666666,
          0.0,
          0.5
        ],
        "results": {
          "1.1111111111111112": {
            "score": Infinity,
            "cost": -1,
            "info": {}
          }
        }
      },
      {
        "config_id": 7,
        "config": [
          0.6511627906976745,
          0.3431151241534989,
          0.8275862068965517,
          0.2,
          0.0,
          0.009523809523809525,
          0.5,
          0.8169014084507042,
          0.5,
          0.8,
          0.75,
          0.8806523350630097,
          0.38332165381920114,
          0.8,
          0.26666666666666666,
          0.0,
          0.25,
          0.0,
          0.75,
          0.675,
          0.14285714285714285,
          0.0,
          0.0,
          0.0,
          0.3333333333333333,
          0.0,
          0.3333333333333333,
          0.5,
          0.6666666666666666,
          0.6666666666666666,
          0.0,
          0.0
        ],
        "results": {
          "1.1111111111111112": {
            "score": Infinity,
            "cost": -1,
            "info": {}
          }
        }
      },
      {
        "config_id": 8,
        "config": [
          0.09302325581395349,
          0.007900677200902935,
          0.5172413793103449,
          0.2,
          0.0,
          0.6884353741496598,
          0.25,
          0.2112676056338028,
          0.25,
          0.6,
          0.25,
          0.429948109710897,
          0.1751927119831815,
          0.8,
          0.3333333333333333,
          0.0,
          0.25,
          0.0,
          0.0,
          0.25,
          0.0,
          0.25,
          0.9375,
          0.0,
          0.0,
          0.0,
          0.5,
          0.5,
          0.6666666666666666,
          0.6666666666666666,
          0.0,
          0.0
        ],
        "results": {
          "1.1111111111111112": {
            "score": Infinity,
            "cost": -1,
            "info": {}
          }
        }
      },
      {
        "config_id": 9,
        "config": [
          0.8372093023255814,
          0.44808126410835214,
          0.10344827586206896,
          0.4,
          0.0,
          0.16802721088435374,
          0.0,
          0.4084507042253521,
          0.0,
          0.8,
          0.5,
          0.5329873980726464,
          0.22424667133847231,
          0.5,
          0.0,
          0.5,
          0.5,
          0.0,
          0.5,
          0.8,
          0.7142857142857143,
          0.25,
          0.3125,
          0.0,
          0.0,
          0.0,
          0.3333333333333333,
          0.5,
          0.4444444444444444,
          0.0,
          0.0,
          0.5
        ],
        "results": {
          "3.333333333333333": {
            "score": Infinity,
            "cost": -1,
            "info": {}
          }
        }
      },
      {
        "config_id": 10,
        "config": [
          0.9302325581395349,
          0.3747178329571106,
          0.41379310344827586,
          0.4,
          0.0,
          0.3585034013605442,
          0.5,
          0.7746478873239436,
          0.0,
          0.8,
          0.5,
          0.9065974796145293,
          0.34407848633496846,
          0.1,
          0.5333333333333333,
          0.5,
          0.0,
          0.0,
          0.25,
          0.175,
          0.8571428571428571,
          0.75,
          0.0,
          0.0,
          0.3333333333333333,
          0.6666666666666666,
          0.16666666666666666,
          0.0,
          0.8888888888888888,
          0.0,
          0.0,
          0.5
        ],
        "results": {
          "3.333333333333333": {
            "score": Infinity,
            "cost": -1,
            "info": {}
          }
        }
      },
      {
        "config_id": 11,
        "config": [
          0.0,
          0.6839729119638827,
          0.6896551724137931,
          0.0,
          0.0,
          0.9863945578231292,
          0.25,
          0.9154929577464789,
          0.25,
          0.2,
          0.0,
          0.6078576723498889,
          0.10371408549404344,
          0.9,
          0.8666666666666667,
          0.5,
          0.75,
          0.0,
          0.5,
          0.425,
          0.7142857142857143,
          0.75,
          0.3125,
          0.5,
          0.6666666666666666,
          0.6666666666666666,
          0.16666666666666666,
          0.5,
          0.2222222222222222,
          0.6666666666666666,
          0.0,
          0.5
        ],
        "results": {
          "3.333333333333333": {
            "score": Infinity,
            "cost": -1,
            "info": {}
          }
        }
      },
      {
        "config_id": 12,
        "config": [
          0.7441860465116279,
          0.4887133182844244,
          0.7241379310344828,
          0.8,
          0.0,
          0.2693877551020408,
          0.25,
          0.29577464788732394,
          0.25,
          0.6,
          0.5,
          0.07042253521126761,
          0.6426068675543097,
          0.2,
          0.0,
          0.5,
          0.75,
          0.0,
          0.0,
          0.2,
          0.42857142857142855,
          0.0,
          0.8125,
          0.0,
          0.3333333333333333,
          0.3333333333333333,
          0.6666666666666666,
          0.5,
          0.8888888888888888,
          0.3333333333333333,
          0.0,
          0.5
        ],
        "results": {
          "10.0": {
            "score": Infinity,
            "cost": -1,
            "info": {}
          }
        }
      },
      {
        "config_id": 13,
        "config": [
          0.8372093023255814,
          0.16252821670428894,
          0.8620689655172413,
          0.4,
          0.0,
          0.14217687074829932,
          0.75,
          0.11267605633802817,
          0.25,
          0.6,
          0.5,
          0.8005930318754633,
          0.8409250175192712,
          0.0,
          0.4666666666666667,
          0.0,
          0.5,
          0.0,
          0.0,
          0.15,
          0.42857142857142855,
          0.0,
          0.8125,
          0.5,
          0.0,
          0.6666666666666666,
          0.3333333333333333,
          0.0,
          0.2222222222222222,
          0.3333333333333333,
          0.0,
          0.5
        ],
        "results": {
          "10.0": {
            "score": Infinity,
            "cost": -1,
            "info": {}
          }
        }
      },
      {
        "config_id": 14,
        "config": [
          0.627906976744186,
          0.09255079006772009,
          0.5862068965517241,
          0.6,
          0.0,
          0.8925170068027211,
          0.75,
          0.11267605633802817,
          0.5,
          0.0,
          0.5,
          0.08895478131949593,
          0.46461107217939734,
          0.1,
          0.4666666666666667,
          0.5,
          0.25,
          0.0,
          0.25,
          0.725,
          0.0,
          0.25,
          0.125,
          0.5,
          0.0,
          0.0,
          0.16666666666666666,
          0.5,
          0.2222222222222222,
          0.0,
          0.0,
          0.5
        ],
        "results": {
          "10.0": {
            "score": Infinity,
            "cost": -1,
            "info": {}
          }
        }
      }
    ]
  }
}